{
  "protocol_version" : "0.0.3",
  "configuration" : {
    "version" : "(5.18.1.3) (tarball)",
    "tlc" : "__thread",
    "sigsgev" : "altstack",
    "notifications" : "epoll",
    "architecture" : "amd64",
    "disabled_features" : "none",
    "smallconfig" : "disabled",
    "bigarrays" : "disabled",
    "softdebug" : "enabled",
    "interpreter" : "enabled",
    "llvm_support" : "disabled",
    "suspend" : "preemptive"
  },
  "memory" : {
    "minor_gc_time" : "2570",
    "major_gc_time" : "70217",
    "minor_gc_count" : "3",
    "major_gc_count" : "12",
    "major_gc_time_concurrent" : "0"
 },
  "threads" : [
 {
    "is_managed" : false,
    "offset_free_hash" : "0x0",
    "offset_rich_hash" : "0x0",
    "crashed" : false,
    "native_thread_id" : "0x7fed4c3fe700",
    "thread_info_addr" : "0x7fed20000b20",
    "thread_name" : "Finalizer",
    "ctx" : {
      "IP" : "0x7fed5d686d16",
      "SP" : "0x7fed4c3fdbe0",
      "BP" : "0x458a840"
  },
    "unmanaged_frames" : [
  {
      "native_address" : "unregistered"
   }
,
  {
      "native_address" : "unregistered"
   }
,
  {
      "native_address" : "unregistered"
   }
,
  {
      "native_address" : "unregistered"
   }
,
  {
      "native_address" : "unregistered"
   }
,
  {
      "native_address" : "unregistered"
   }
,
  {
      "native_address" : "unregistered"
   }
,
  {
      "native_address" : "unregistered"
   }
,
  {
      "native_address" : "unregistered"
   }
,
  {
      "native_address" : "unregistered"
   }
,
  {
      "native_address" : "unregistered"
   }

  ]
 },
 {
    "is_managed" : false,
    "offset_free_hash" : "0x0",
    "offset_rich_hash" : "0x0",
    "crashed" : true,
    "native_thread_id" : "0x7fed5b9e9840",
    "thread_info_addr" : "0x7158500",
    "thread_name" : "Godot_v3.1.1-st",
    "ctx" : {
      "IP" : "0xc1b580",
      "SP" : "0x7ffcc84eeb5c",
      "BP" : "0x7ffcc84eeb5c"
  },
    "unmanaged_frames" : [
  {
      "native_address" : "unregistered"
   }
,
  {
      "native_address" : "unregistered"
   }
,
  {
      "native_address" : "unregistered"
   }
,
  {
      "native_address" : "unregistered"
   }
,
  {
      "native_address" : "unregistered"
   }
,
  {
      "native_address" : "unregistered"
   }
,
  {
      "native_address" : "unregistered"
   }
,
  {
      "native_address" : "unregistered"
   }
,
  {
      "native_address" : "unregistered"
   }

  ]
 },
 {
    "is_managed" : false,
    "offset_free_hash" : "0x0",
    "offset_rich_hash" : "0x0",
    "crashed" : false,
    "native_thread_id" : "0x7fed245a2700",
    "thread_info_addr" : "0x7fed040012b0",
    "thread_name" : "Thread Pool Wor",
    "ctx" : {
      "IP" : "0x7fed5d686f42",
      "SP" : "0x7fed245a1be0",
      "BP" : "0x4592148"
  },
    "unmanaged_frames" : [
  {
      "native_address" : "unregistered"
   }
,
  {
      "native_address" : "unregistered"
   }
,
  {
      "native_address" : "unregistered"
   }
,
  {
      "native_address" : "unregistered"
   }
,
  {
      "native_address" : "unregistered"
   }
,
  {
      "native_address" : "unregistered"
   }
,
  {
      "native_address" : "unregistered"
   }
,
  {
      "native_address" : "unregistered"
   }
,
  {
      "native_address" : "unregistered"
   }
,
  {
      "native_address" : "unregistered"
   }
,
  {
      "native_address" : "unregistered"
   }

  ]
 },
 {
    "is_managed" : false,
    "offset_free_hash" : "0x0",
    "offset_rich_hash" : "0x0",
    "crashed" : false,
    "native_thread_id" : "0x7fed249a4700",
    "thread_info_addr" : "0x7fed0c000b20",
    "thread_name" : "Thread Pool Wor",
    "ctx" : {
      "IP" : "0x7fed5d686f42",
      "SP" : "0x7fed249a3be0",
      "BP" : "0x4592148"
  },
    "unmanaged_frames" : [
  {
      "native_address" : "unregistered"
   }
,
  {
      "native_address" : "unregistered"
   }
,
  {
      "native_address" : "unregistered"
   }
,
  {
      "native_address" : "unregistered"
   }
,
  {
      "native_address" : "unregistered"
   }
,
  {
      "native_address" : "unregistered"
   }
,
  {
      "native_address" : "unregistered"
   }
,
  {
      "native_address" : "unregistered"
   }
,
  {
      "native_address" : "unregistered"
   }
,
  {
      "native_address" : "unregistered"
   }
,
  {
      "native_address" : "unregistered"
   }

  ]
 },
 {
    "is_managed" : false,
    "offset_free_hash" : "0x0",
    "offset_rich_hash" : "0x0",
    "crashed" : false,
    "native_thread_id" : "0x7fecffdfe700",
    "thread_info_addr" : "0x7fecec0008d0",
    "thread_name" : "Thread Pool Wor",
    "ctx" : {
      "IP" : "0x7fed5d686f42",
      "SP" : "0x7fecffdfdbe0",
      "BP" : "0x4592148"
  },
    "unmanaged_frames" : [
  {
      "native_address" : "unregistered"
   }
,
  {
      "native_address" : "unregistered"
   }
,
  {
      "native_address" : "unregistered"
   }
,
  {
      "native_address" : "unregistered"
   }
,
  {
      "native_address" : "unregistered"
   }
,
  {
      "native_address" : "unregistered"
   }
,
  {
      "native_address" : "unregistered"
   }
,
  {
      "native_address" : "unregistered"
   }
,
  {
      "native_address" : "unregistered"
   }
,
  {
      "native_address" : "unregistered"
   }
,
  {
      "native_address" : "unregistered"
   }

  ]
 },
 {
    "is_managed" : false,
    "offset_free_hash" : "0x0",
    "offset_rich_hash" : "0x0",
    "crashed" : false,
    "native_thread_id" : "0x7fed275ff700",
    "thread_info_addr" : "0x7fed14000fb0",
    "thread_name" : "Godot_v3.1.1-st",
    "ctx" : {
      "IP" : "0x7fed5d68477c",
      "SP" : "0x7fed275feb30",
      "BP" : "0x459dbe0"
  },
    "unmanaged_frames" : [
  {
      "native_address" : "unregistered"
   }
,
  {
      "native_address" : "unregistered"
   }
,
  {
      "native_address" : "unregistered"
   }
,
  {
      "native_address" : "unregistered"
   }
,
  {
      "native_address" : "unregistered"
   }
,
  {
      "native_address" : "unregistered"
   }
,
  {
      "native_address" : "unregistered"
   }
,
  {
      "native_address" : "unregistered"
   }
,
  {
      "native_address" : "unregistered"
   }
,
  {
      "native_address" : "unregistered"
   }
,
  {
      "native_address" : "unregistered"
   }
,
  {
      "native_address" : "unregistered"
   }

  ]
 },
 {
    "is_managed" : false,
    "offset_free_hash" : "0x0",
    "offset_rich_hash" : "0x0",
    "crashed" : false,
    "native_thread_id" : "0x7fecfffff700",
    "thread_info_addr" : "0x7fecf40014d0",
    "thread_name" : "Thread Pool Wor",
    "ctx" : {
      "IP" : "0x7fed5d686f42",
      "SP" : "0x7fecffffebe0",
      "BP" : "0x4592148"
  },
    "unmanaged_frames" : [
  {
      "native_address" : "unregistered"
   }
,
  {
      "native_address" : "unregistered"
   }
,
  {
      "native_address" : "unregistered"
   }
,
  {
      "native_address" : "unregistered"
   }
,
  {
      "native_address" : "unregistered"
   }
,
  {
      "native_address" : "unregistered"
   }
,
  {
      "native_address" : "unregistered"
   }
,
  {
      "native_address" : "unregistered"
   }
,
  {
      "native_address" : "unregistered"
   }
,
  {
      "native_address" : "unregistered"
   }
,
  {
      "native_address" : "unregistered"
   }

  ]
 },
 {
    "is_managed" : false,
    "offset_free_hash" : "0x0",
    "offset_rich_hash" : "0x0",
    "crashed" : false,
    "native_thread_id" : "0x7fed247a3700",
    "thread_info_addr" : "0x7fed00003510",
    "thread_name" : "Thread Pool Wor",
    "ctx" : {
      "IP" : "0x7fed5d686f42",
      "SP" : "0x7fed247a2be0",
      "BP" : "0x4592148"
  },
    "unmanaged_frames" : [
  {
      "native_address" : "unregistered"
   }
,
  {
      "native_address" : "unregistered"
   }
,
  {
      "native_address" : "unregistered"
   }
,
  {
      "native_address" : "unregistered"
   }
,
  {
      "native_address" : "unregistered"
   }
,
  {
      "native_address" : "unregistered"
   }
,
  {
      "native_address" : "unregistered"
   }
,
  {
      "native_address" : "unregistered"
   }
,
  {
      "native_address" : "unregistered"
   }
,
  {
      "native_address" : "unregistered"
   }
,
  {
      "native_address" : "unregistered"
   }

  ]
 },
 {
    "is_managed" : false,
    "offset_free_hash" : "0x0",
    "offset_rich_hash" : "0x0",
    "crashed" : false,
    "native_thread_id" : "0x7fed243a1700",
    "thread_info_addr" : "0x7fecf8000b20",
    "thread_name" : "Thread Pool Wor",
    "ctx" : {
      "IP" : "0x7fed5d686f42",
      "SP" : "0x7fed243a0be0",
      "BP" : "0x4592148"
  },
    "unmanaged_frames" : [
  {
      "native_address" : "unregistered"
   }
,
  {
      "native_address" : "unregistered"
   }
,
  {
      "native_address" : "unregistered"
   }
,
  {
      "native_address" : "unregistered"
   }
,
  {
      "native_address" : "unregistered"
   }
,
  {
      "native_address" : "unregistered"
   }
,
  {
      "native_address" : "unregistered"
   }
,
  {
      "native_address" : "unregistered"
   }
,
  {
      "native_address" : "unregistered"
   }
,
  {
      "native_address" : "unregistered"
   }
,
  {
      "native_address" : "unregistered"
   }

  ]
 }
 ]
}